html_processor/__init__.py
html_processor/processor.py
html_processor/rules.py
html_processor-0.0.5.dist-info/LICENSE
html_processor-0.0.5.dist-info/WHEEL
html_processor-0.0.5.dist-info/METADATA
html_processor-0.0.5.dist-info/RECORD
