Metadata-Version: 2.1
Name: html-processor
Version: 0.0.5
Summary: Package that provides a set of classes around BeautifulSoup for easy HTML modification.
Home-page: https://github.com/brogency/html-processor
License: MIT
Keywords: html,processing,bs4,BeautifulSoup
Author: Дмитрий
Author-email: acrius@mail.ru
Requires-Python: >=3.6,<4.0
Classifier: License :: OSI Approved :: MIT License
Classifier: Programming Language :: Python :: 3
Classifier: Programming Language :: Python :: 3.6
Classifier: Programming Language :: Python :: 3.7
Classifier: Topic :: Text Processing :: Markup :: HTML
Requires-Dist: bs4 (>=0.0.1,<0.0.2)
Project-URL: Documentation, https://github.com/brogency/html-processor
Project-URL: Repository, https://github.com/brogency/html-processor
